dafni_cli/__init__.py
dafni_cli/consts.py
dafni_cli/dafni.py
dafni_cli/filtering.py
dafni_cli/utils.py
dafni_cli/version.py
dafni_cli/api/__init__.py
dafni_cli/api/auth.py
dafni_cli/api/datasets_api.py
dafni_cli/api/exceptions.py
dafni_cli/api/minio_api.py
dafni_cli/api/models_api.py
dafni_cli/api/notifications_api.py
dafni_cli/api/parser.py
dafni_cli/api/session.py
dafni_cli/api/workflows_api.py
dafni_cli/commands/__init__.py
dafni_cli/commands/create.py
dafni_cli/commands/delete.py
dafni_cli/commands/download.py
dafni_cli/commands/get.py
dafni_cli/commands/helpers.py
dafni_cli/commands/login.py
dafni_cli/commands/options.py
dafni_cli/commands/upload.py
dafni_cli/commands/validate.py
dafni_cli/data/__init__.py
dafni_cli/data/dataset_metadata_template.json
dafni_cli/datasets/__init__.py
dafni_cli/datasets/dataset.py
dafni_cli/datasets/dataset_download.py
dafni_cli/datasets/dataset_filtering.py
dafni_cli/datasets/dataset_metadata.py
dafni_cli/datasets/dataset_upload.py
dafni_cli/models/__init__.py
dafni_cli/models/inputs.py
dafni_cli/models/model.py
dafni_cli/models/outputs.py
dafni_cli/models/upload.py
dafni_cli/tests/__init__.py
dafni_cli/tests/test_consts.py
dafni_cli/tests/test_filtering.py
dafni_cli/tests/test_utils.py
dafni_cli/tests/api/__init__.py
dafni_cli/tests/api/test_auth.py
dafni_cli/tests/api/test_datasets_api.py
dafni_cli/tests/api/test_minio_api.py
dafni_cli/tests/api/test_models_api.py
dafni_cli/tests/api/test_notifications_api.py
dafni_cli/tests/api/test_parser.py
dafni_cli/tests/api/test_session.py
dafni_cli/tests/api/test_workflows_api.py
dafni_cli/tests/commands/__init__.py
dafni_cli/tests/commands/test_create.py
dafni_cli/tests/commands/test_delete.py
dafni_cli/tests/commands/test_download.py
dafni_cli/tests/commands/test_get.py
dafni_cli/tests/commands/test_helpers.py
dafni_cli/tests/commands/test_login.py
dafni_cli/tests/commands/test_options.py
dafni_cli/tests/commands/test_upload.py
dafni_cli/tests/commands/test_validate.py
dafni_cli-1.2.0.dist-info/licenses/LICENSE
dafni_cli-1.2.0.dist-info/METADATA
dafni_cli-1.2.0.dist-info/WHEEL
dafni_cli-1.2.0.dist-info/entry_points.txt
dafni_cli-1.2.0.dist-info/top_level.txt
dafni_cli-1.2.0.dist-info/RECORD
