Metadata-Version: 2.4
Name: dafni-cli
Version: 1.2.0
Summary: A CLI to access the DAFNI APIs from the command line
Author-email: DAFNI Facility <support@dafni.ac.uk>
Project-URL: Documentation, https://github.com/dafnifacility/cli/blob/main/docs/dafni_cli.md
Project-URL: Release notes, https://github.com/dafnifacility/cli/releases
Project-URL: Source, https://github.com/dafnifacility/cli
Project-URL: Issue Tracker, https://github.com/dafnifacility/cli/issues
Classifier: Programming Language :: Python :: 3
Classifier: License :: OSI Approved :: MIT License
Classifier: Operating System :: OS Independent
Requires-Python: >=3.9
License-File: LICENSE
Requires-Dist: click>=8.1.6
Requires-Dist: requests>=2.31.0
Requires-Dist: python-dateutil>=2.8.2
Requires-Dist: tabulate>=0.9.0
Requires-Dist: tqdm>=4.65.0
Dynamic: license-file
